ciunittest.py
CIUnitTest-1.0.9.dist-info/DESCRIPTION.rst
CIUnitTest-1.0.9.dist-info/METADATA
CIUnitTest-1.0.9.dist-info/RECORD
CIUnitTest-1.0.9.dist-info/WHEEL
CIUnitTest-1.0.9.dist-info/metadata.json
CIUnitTest-1.0.9.dist-info/top_level.txt
