Metadata-Version: 2.0
Name: CIUnitTest
Version: 1.0.9
Summary: Provides test results of unittest in JSON format, in order to be able to use the results programmatically.
Home-page: http://go.pelicandd.com/n/python-ciunittest
Author: Arseni Mourzenko
Author-email: arseni.mourzenko@pelicandd.com
License: MIT
Keywords: unittest ci continuous-integration json
Platform: UNKNOWN
